killcmd.py
netstatm.py
setup.py
sync_iterm_profile.py
mafia_ops_tools.egg-info/PKG-INFO
mafia_ops_tools.egg-info/SOURCES.txt
mafia_ops_tools.egg-info/dependency_links.txt
mafia_ops_tools.egg-info/entry_points.txt
mafia_ops_tools.egg-info/top_level.txt