Metadata-Version: 1.0
Name: mafia-ops-tools
Version: 0.5
Summary: command line toolset to help you better manage servers.
Home-page: https://github.com/superluffy/ops_tools
Author: yanbin
Author-email: yanb1985@gmail.com
License: MIT License
Keywords: ops,tools,server,ubuntu,op
Platform: UNKNOWN
